tree_maker/__init__.py
tree_maker/__main__.py
tree_maker/config.py
tree_maker/tree.py
tree_maker/utils.py
tree_maker_cli-1.0.3.dist-info/licenses/LICENSE
tree_maker_cli-1.0.3.dist-info/METADATA
tree_maker_cli-1.0.3.dist-info/WHEEL
tree_maker_cli-1.0.3.dist-info/entry_points.txt
tree_maker_cli-1.0.3.dist-info/top_level.txt
tree_maker_cli-1.0.3.dist-info/RECORD
