Metadata-Version: 2.4
Name: tree_maker_cli
Version: 1.0.3
Summary: A command-line tool to generate a tree structure of a folder and its contents, useful for when you need to add context to your GPT prompts.
Home-page: https://github.com/tecz/tree_maker_cli
Author: Timothy Czerniec
Author-email: teczerniec@gmail.com
License: MIT
Keywords: tree tree-maker cli folder structure
License-File: LICENSE
Requires-Dist: pyperclip
Dynamic: author
Dynamic: author-email
Dynamic: description
Dynamic: description-content-type
Dynamic: home-page
Dynamic: keywords
Dynamic: license
Dynamic: license-file
Dynamic: requires-dist
Dynamic: summary
